surquest/GCP/requirements.txt
surquest/GCP/dataform_cli/__init__.py
surquest/GCP/dataform_cli/__main__.py
surquest/GCP/dataform_cli/logger.py
surquest/GCP/dataform_cli/pull.py
surquest/GCP/dataform_cli/push.py
surquest/GCP/dataform_cli/handlers/__init__.py
surquest/GCP/dataform_cli/handlers/dataform_handler.py
surquest/GCP/dataform_cli/handlers/gitignore_handler.py
surquest/GCP/dataform_cli/handlers/pull_handler.py
surquest/GCP/dataform_cli/handlers/push_handler.py
surquest_gcp_dataform_cli-0.0.1rc2.dist-info/METADATA
surquest_gcp_dataform_cli-0.0.1rc2.dist-info/WHEEL
surquest_gcp_dataform_cli-0.0.1rc2.dist-info/entry_points.txt
surquest_gcp_dataform_cli-0.0.1rc2.dist-info/licenses/LICENSE
surquest_gcp_dataform_cli-0.0.1rc2.dist-info/RECORD
