Metadata-Version: 2.4
Name: surquest-GCP-dataform-cli
Version: 0.0.1rc2
Summary: `dataform_cli` is a lightweight Python-based command-line interface (CLI) designed to simplify **file synchronization between local directories and Google Cloud Dataform workspaces**.
Project-URL: Homepage, https://github.com/surquest/python-dataform-cli
Project-URL: Bug Tracker, https://github.com/surquest/python-dataform-cli/issues
Author-email: Michal Švarc <michal.svarc@surquest.com>
License-File: LICENSE
Requires-Dist: google-cloud-dataform>=0.6.0
Requires-Dist: pathspec>=0.12.0
Provides-Extra: test
Requires-Dist: pytest-cov>=4.0.0; extra == 'test'
Requires-Dist: pytest>=7.2.1; extra == 'test'
